STOUT/__init__.py
STOUT/predictor_demo.py
STOUT/stout.py
STOUT/repack/helper.py
STOUT/repack/repack_model.py
STOUT/repack/transformer_model_4_repack.py
STOUT/trainer/STOUT_V2_Trainer.py
STOUT/trainer/nmt_model_transformer.py
STOUT_pypi-2.1.0.dist-info/LICENSE
STOUT_pypi-2.1.0.dist-info/METADATA
STOUT_pypi-2.1.0.dist-info/WHEEL
STOUT_pypi-2.1.0.dist-info/top_level.txt
STOUT_pypi-2.1.0.dist-info/RECORD
