Metadata-Version: 2.1
Name: STOUT-pypi
Version: 2.1.0
Summary: STOUT V2.0 - Smiles TO iUpac Translator Version 2.0
Home-page: https://github.com/Kohulan/Smiles-TO-iUpac-Translator
Author: Kohulan Rajan
Author-email: kohulan.rajan@uni-jena.de
Maintainer: Kohulan Rajan
Maintainer-email: kohulan.rajan@uni-jena.de
License: MIT
Classifier: Programming Language :: Python :: 3
Classifier: Programming Language :: Python :: 3.8
Classifier: Programming Language :: Python :: 3.9
Classifier: Programming Language :: Python :: 3.10
Classifier: Programming Language :: Python :: 3 :: Only
Classifier: License :: OSI Approved :: MIT License
Classifier: Operating System :: OS Independent
Requires-Python: >=3.7
License-File: LICENSE
Requires-Dist: tensorflow-macos ==2.15.0
Requires-Dist: pystow
Requires-Dist: unicodedata2
Requires-Dist: jpype1
Requires-Dist: rdkit
